{
  "title":"Manifiesto para la Artesanía del Software",
  "raising_the_bar":"Subiendo el nivel.",
  "introduction":"Como aspirantes a Artesanos del Software estamos elevando el listón de desarrollo de software profesional practicando y ayudando a otros a aprender el oficio. A través de este trabajo hemos llegado a valorar:",
  "not_only":"No sólo ",
  "but_also":"sino también ",
  "working_software":"software que funciona,",
  "well_crafted_software":"software bien diseñado",
  "responding_to_change":"responder al cambio,",
  "steadily_adding_value":"agregar valor constantemente",
  "individuals_and_interactions":"individuos e interacciones,",
  "a_community_of_professionals":"una comunidad de profesionales",
  "customer_collaboration":"colaboración de clientes,",
  "productive_partnerships":"asociaciones productivas",
  "conclusion":"Es decir, en la búsqueda de los elementos de la izquierda, hemos encontrado indispensables los elementos de la derecha.",
  "copyright":"\u00a9 2009, los firmantes.",
  "this_statement_may_be_freely_copied_in_any_form":"esta declaración puede ser libremente copiada en cualquier forma,",
  "but_only_in_its_entirety_through_this_notice":"pero solamente en su totalidad a través de este aviso.",
  "sign_the_manifesto":"Firma el Manifiesto",
  "view_map":"Mira el mapa",
  "further_reading":"Lectura Adicional",
  "design_by":"Diseño por",
  "metrics": "Métricas"
}
